[
  {
    "id": 1,
    "src_country": "Indonesia",
    "dest_country": "China",
    "date": "11/24/04"
  },
  {
    "id": 2,
    "src_country": "Indonesia",
    "dest_country": "Japan",
    "date": "03/22/05"
  },
  {
    "id": 3,
    "src_country": "Indonesia",
    "dest_country": "United States",
    "date": "06/02/05"
  },
  {
    "id": 4,
    "src_country": "Indonesia",
    "dest_country": "Germany",
    "date": "06/14/05"
  },
  {
    "id": 5,
    "src_country": "Indonesia",
    "dest_country": "Russia",
    "date": "07/01/05"
  },
  {
    "id": 6,
    "src_country": "Indonesia",
    "dest_country": "Vietnam",
    "date": "08/31/05"
  },
  {
    "id": 7,
    "src_country": "Indonesia",
    "dest_country": "India",
    "date": "09/01/05"
  },
  {
    "id": 8,
    "src_country": "China",
    "dest_country": "Indonesia",
    "date": "10/01/05"
  },
  {
    "id": 9,
    "src_country": "China",
    "dest_country": "Indonesia",
    "date": "11/14/05"
  },
  {
    "id": 10,
    "src_country": "China",
    "dest_country": "Indonesia",
    "date": "12/09/05"
  },
  {
    "id": 11,
    "src_country": "China",
    "dest_country": "Indonesia",
    "date": "02/14/06"
  },
  {
    "id": 12,
    "src_country": "China",
    "dest_country": "Indonesia",
    "date": "04/06/06"
  },
  {
    "id": 13,
    "src_country": "China",
    "dest_country": "Indonesia",
    "date": "05/26/06"
  },
  {
    "id": 14,
    "src_country": "China",
    "dest_country": "Indonesia",
    "date": "06/14/06"
  },
  {
    "id": 15,
    "src_country": "Indonesia",
    "dest_country": "United States",
    "date": "07/07/06"
  },
  {
    "id": 16,
    "src_country": "Indonesia",
    "dest_country": "United States",
    "date": "08/03/06"
  },
  {
    "id": 17,
    "src_country": "Indonesia",
    "dest_country": "United States",
    "date": "09/14/06"
  },
  {
    "id": 18,
    "src_country": "Indonesia",
    "dest_country": "United States",
    "date": "10/25/06"
  },
  {
    "id": 19,
    "src_country": "Indonesia",
    "dest_country": "United States",
    "date": "11/20/06"
  },
  {
    "id": 20,
    "src_country": "Indonesia",
    "dest_country": "United States",
    "date": "12/21/06"
  },
  {
    "id": 21,
    "src_country": "Indonesia",
    "dest_country": "United States",
    "date": "01/23/07"
  },
  {
    "id": 22,
    "src_country": "Germany",
    "dest_country": "Indonesia",
    "date": "01/30/07"
  },
  {
    "id": 23,
    "src_country": "Germany",
    "dest_country": "Indonesia",
    "date": "02/25/07"
  },
  {
    "id": 24,
    "src_country": "Germany",
    "dest_country": "Indonesia",
    "date": "03/16/07"
  },
  {
    "id": 25,
    "src_country": "Germany",
    "dest_country": "Indonesia",
    "date": "04/13/07"
  },
  {
    "id": 26,
    "src_country": "Germany",
    "dest_country": "Indonesia",
    "date": "05/24/07"
  },
  {
    "id": 27,
    "src_country": "Germany",
    "dest_country": "Indonesia",
    "date": "06/16/07"
  },
  {
    "id": 28,
    "src_country": "Germany",
    "dest_country": "Indonesia",
    "date": "07/23/07"
  },
  {
    "id": 29,
    "src_country": "Indonesia",
    "dest_country": "Russia",
    "date": "08/13/07"
  },
  {
    "id": 30,
    "src_country": "Indonesia",
    "dest_country": "Russia",
    "date": "09/06/07"
  },
  {
    "id": 31,
    "src_country": "Indonesia",
    "dest_country": "Russia",
    "date": "10/19/07"
  },
  {
    "id": 32,
    "src_country": "Indonesia",
    "dest_country": "Russia",
    "date": "11/12/07"
  },
  {
    "id": 33,
    "src_country": "Indonesia",
    "dest_country": "Russia",
    "date": "12/11/07"
  },
  {
    "id": 34,
    "src_country": "Indonesia",
    "dest_country": "Russia",
    "date": "01/01/08"
  },
  {
    "id": 35,
    "src_country": "Indonesia",
    "dest_country": "Russia",
    "date": "02/06/08"
  },
  {
    "id": 36,
    "src_country": "Vietnam",
    "dest_country": "Indonesia",
    "date": "03/01/08"
  },
  {
    "id": 37,
    "src_country": "Vietnam",
    "dest_country": "Indonesia",
    "date": "04/01/08"
  },
  {
    "id": 38,
    "src_country": "Vietnam",
    "dest_country": "Indonesia",
    "date": "06/17/08"
  },
  {
    "id": 39,
    "src_country": "Vietnam",
    "dest_country": "Indonesia",
    "date": "07/03/08"
  },
  {
    "id": 40,
    "src_country": "Vietnam",
    "dest_country": "Indonesia",
    "date": "09/18/08"
  },
  {
    "id": 41,
    "src_country": "Vietnam",
    "dest_country": "Indonesia",
    "date": "10/08/08"
  },
  {
    "id": 42,
    "src_country": "Vietnam",
    "dest_country": "Indonesia",
    "date": "11/19/08"
  },
  {
    "id": 43,
    "src_country": "Indonesia",
    "dest_country": "India",
    "date": "12/18/08"
  },
  {
    "id": 44,
    "src_country": "Indonesia",
    "dest_country": "India",
    "date": "01/20/09"
  },
  {
    "id": 45,
    "src_country": "Indonesia",
    "dest_country": "India",
    "date": "02/13/09"
  },
  {
    "id": 46,
    "src_country": "Indonesia",
    "dest_country": "India",
    "date": "03/20/09"
  },
  {
    "id": 47,
    "src_country": "Indonesia",
    "dest_country": "India",
    "date": "04/10/09"
  },
  {
    "id": 48,
    "src_country": "Indonesia",
    "dest_country": "India",
    "date": "07/20/09"
  },
  {
    "id": 49,
    "src_country": "Indonesia",
    "dest_country": "India",
    "date": "08/10/09"
  },
  {
    "id": 50,
    "src_country": "India",
    "dest_country": "Indonesia",
    "date": "09/15/09"
  },
  {
    "id": 51,
    "src_country": "India",
    "dest_country": "Indonesia",
    "date": "10/19/09"
  },
  {
    "id": 52,
    "src_country": "India",
    "dest_country": "Indonesia",
    "date": "11/06/09"
  },
  {
    "id": 53,
    "src_country": "India",
    "dest_country": "Indonesia",
    "date": "12/17/09"
  },
  {
    "id": 54,
    "src_country": "India",
    "dest_country": "Indonesia",
    "date": "02/16/10"
  },
  {
    "id": 55,
    "src_country": "India",
    "dest_country": "Indonesia",
    "date": "03/14/10"
  },
  {
    "id": 56,
    "src_country": "India",
    "dest_country": "Indonesia",
    "date": "04/14/10"
  },
  {
    "id": 57,
    "src_country": "Indonesia",
    "dest_country": "Vietnam",
    "date": "05/05/10"
  },
  {
    "id": 58,
    "src_country": "Indonesia",
    "dest_country": "Vietnam",
    "date": "06/19/10"
  },
  {
    "id": 59,
    "src_country": "Indonesia",
    "dest_country": "Vietnam",
    "date": "07/01/10"
  },
  {
    "id": 60,
    "src_country": "Indonesia",
    "dest_country": "Vietnam",
    "date": "08/24/10"
  },
  {
    "id": 61,
    "src_country": "Indonesia",
    "dest_country": "Vietnam",
    "date": "09/01/10"
  },
  {
    "id": 62,
    "src_country": "Indonesia",
    "dest_country": "Vietnam",
    "date": "10/19/10"
  },
  {
    "id": 63,
    "src_country": "Indonesia",
    "dest_country": "Vietnam",
    "date": "11/06/10"
  },
  {
    "id": 64,
    "src_country": "Vietnam",
    "dest_country": "Indonesia",
    "date": "12/27/10"
  },
  {
    "id": 65,
    "src_country": "Vietnam",
    "dest_country": "Indonesia",
    "date": "01/18/11"
  },
  {
    "id": 66,
    "src_country": "Vietnam",
    "dest_country": "Indonesia",
    "date": "02/22/11"
  },
  {
    "id": 67,
    "src_country": "Vietnam",
    "dest_country": "Indonesia",
    "date": "03/11/11"
  },
  {
    "id": 68,
    "src_country": "Vietnam",
    "dest_country": "Indonesia",
    "date": "04/26/11"
  },
  {
    "id": 69,
    "src_country": "Vietnam",
    "dest_country": "Indonesia",
    "date": "05/16/11"
  },
  {
    "id": 70,
    "src_country": "Vietnam",
    "dest_country": "Indonesia",
    "date": "07/14/11"
  },
  {
    "id": 71,
    "src_country": "Indonesia",
    "dest_country": "Germany",
    "date": "09/19/11"
  },
  {
    "id": 72,
    "src_country": "Indonesia",
    "dest_country": "Germany",
    "date": "11/16/11"
  },
  {
    "id": 73,
    "src_country": "Indonesia",
    "dest_country": "Germany",
    "date": "03/28/12"
  },
  {
    "id": 74,
    "src_country": "Indonesia",
    "dest_country": "Germany",
    "date": "04/19/12"
  },
  {
    "id": 75,
    "src_country": "Indonesia",
    "dest_country": "Germany",
    "date": "05/04/12"
  },
  {
    "id": 76,
    "src_country": "Indonesia",
    "dest_country": "Germany",
    "date": "07/19/12"
  },
  {
    "id": 77,
    "src_country": "Indonesia",
    "dest_country": "Germany",
    "date": "08/10/12"
  },
  {
    "id": 78,
    "src_country": "China",
    "dest_country": "Indonesia",
    "date": "09/16/12"
  },
  {
    "id": 79,
    "src_country": "China",
    "dest_country": "Indonesia",
    "date": "10/21/12"
  },
  {
    "id": 80,
    "src_country": "China",
    "dest_country": "Indonesia",
    "date": "11/15/12"
  },
  {
    "id": 81,
    "src_country": "China",
    "dest_country": "Indonesia",
    "date": "12/03/12"
  },
  {
    "id": 82,
    "src_country": "China",
    "dest_country": "Indonesia",
    "date": "01/15/13"
  },
  {
    "id": 83,
    "src_country": "China",
    "dest_country": "Indonesia",
    "date": "03/24/13"
  },
  {
    "id": 84,
    "src_country": "China",
    "dest_country": "Indonesia",
    "date": "04/17/13"
  },
  {
    "id": 85,
    "src_country": "Indonesia",
    "dest_country": "China",
    "date": "05/13/13"
  },
  {
    "id": 86,
    "src_country": "Indonesia",
    "dest_country": "China",
    "date": "06/07/13"
  },
  {
    "id": 87,
    "src_country": "Indonesia",
    "dest_country": "China",
    "date": "07/03/13"
  },
  {
    "id": 88,
    "src_country": "Indonesia",
    "dest_country": "China",
    "date": "08/23/13"
  },
  {
    "id": 89,
    "src_country": "Indonesia",
    "dest_country": "China",
    "date": "09/22/13"
  },
  {
    "id": 90,
    "src_country": "Indonesia",
    "dest_country": "China",
    "date": "10/23/13"
  },
  {
    "id": 91,
    "src_country": "Indonesia",
    "dest_country": "China",
    "date": "11/14/13"
  },
  {
    "id": 92,
    "src_country": "China",
    "dest_country": "Indonesia",
    "date": "12/06/13"
  },
  {
    "id": 93,
    "src_country": "China",
    "dest_country": "Indonesia",
    "date": "02/04/14"
  },
  {
    "id": 94,
    "src_country": "China",
    "dest_country": "Indonesia",
    "date": "04/15/14"
  },
  {
    "id": 95,
    "src_country": "China",
    "dest_country": "Indonesia",
    "date": "07/03/14"
  },
  {
    "id": 96,
    "src_country": "China",
    "dest_country": "Indonesia",
    "date": "08/05/14"
  },
  {
    "id": 97,
    "src_country": "China",
    "dest_country": "Indonesia",
    "date": "09/19/14"
  },
  {
    "id": 98,
    "src_country": "China",
    "dest_country": "Indonesia",
    "date": "10/28/14"
  },
  {
    "id": 99,
    "src_country": "Indonesia",
    "dest_country": "China",
    "date": "11/05/14"
  },
  {
    "id": 100,
    "src_country": "Indonesia",
    "dest_country": "China",
    "date": "12/19/14"
  },
  {
    "id": 101,
    "src_country": "Indonesia",
    "dest_country": "China",
    "date": "02/06/15"
  },
  {
    "id": 102,
    "src_country": "Indonesia",
    "dest_country": "China",
    "date": "03/01/15"
  },
  {
    "id": 103,
    "src_country": "Indonesia",
    "dest_country": "China",
    "date": "04/10/15"
  },
  {
    "id": 104,
    "src_country": "Indonesia",
    "dest_country": "China",
    "date": "05/18/15"
  },
  {
    "id": 105,
    "src_country": "Indonesia",
    "dest_country": "China",
    "date": "06/29/15"
  },
  {
    "id": 106,
    "src_country": "China",
    "dest_country": "Indonesia",
    "date": "08/20/15"
  },
  {
    "id": 107,
    "src_country": "China",
    "dest_country": "Indonesia",
    "date": "09/19/15"
  },
  {
    "id": 108,
    "src_country": "China",
    "dest_country": "Indonesia",
    "date": "10/22/16"
  },
  {
    "id": 109,
    "src_country": "China",
    "dest_country": "Indonesia",
    "date": "12/13/16"
  },
  {
    "id": 110,
    "src_country": "China",
    "dest_country": "Indonesia",
    "date": "02/16/17"
  },
  {
    "id": 111,
    "src_country": "China",
    "dest_country": "Indonesia",
    "date": "03/24/17"
  }
]